isolation/__init__.py
isolation/util.py
isolation/example_dags/isolation_provider_example_dag.py
isolation/hooks/__init__.py
isolation/hooks/post_isolation.py
isolation/operators/__init__.py
isolation/operators/isolation.py
isolation/operators/isolation_kubernetes.py
isolationctl/__init__.py
isolationctl/__main__.py
apache_airflow_providers_isolation-1.0.1.dist-info/LICENSE
apache_airflow_providers_isolation-1.0.1.dist-info/METADATA
apache_airflow_providers_isolation-1.0.1.dist-info/WHEEL
apache_airflow_providers_isolation-1.0.1.dist-info/entry_points.txt
apache_airflow_providers_isolation-1.0.1.dist-info/top_level.txt
apache_airflow_providers_isolation-1.0.1.dist-info/RECORD
