Metadata-Version: 2.1
Name: apache-airflow-providers-isolation
Version: 1.0.1
Summary: Runtime Operator Isolation in Airflow
Author-email: Fritz Davenport <fritz@astronomer.io>, Astronomer <humans@astronomer.io>
License: Apache License 2.0
Project-URL: Homepage, https://astronomer.io
Project-URL: Source, https://github.com/astronomer/apache-airflow-providers-isolation/
Classifier: Framework :: Apache Airflow
Classifier: Framework :: Apache Airflow :: Provider
Requires-Python: <3.12,>=3.8
License-File: LICENSE
Provides-Extra: cli
Requires-Dist: click ; extra == 'cli'
Requires-Dist: docker ; extra == 'cli'
Requires-Dist: sh ; extra == 'cli'
Requires-Dist: pyyaml ; extra == 'cli'
Provides-Extra: dev
Requires-Dist: build ; extra == 'dev'
Requires-Dist: docutils ; extra == 'dev'
Requires-Dist: twine ; extra == 'dev'
Requires-Dist: pytest-sugar ; extra == 'dev'
Requires-Dist: pytest ; extra == 'dev'
Requires-Dist: pytest-cov ; extra == 'dev'
Requires-Dist: pytest-mock ; extra == 'dev'
Requires-Dist: pytest-env ; extra == 'dev'
Requires-Dist: detect-secrets ; extra == 'dev'
Requires-Dist: ruff ; extra == 'dev'
Requires-Dist: black ; extra == 'dev'
Requires-Dist: bandit ; extra == 'dev'
Requires-Dist: pre-commit ; extra == 'dev'
Requires-Dist: pre-commit-hooks ; extra == 'dev'
Requires-Dist: pylint ; extra == 'dev'
Requires-Dist: docker ; extra == 'dev'
Requires-Dist: kubernetes ; extra == 'dev'
Requires-Dist: click ; extra == 'dev'
Requires-Dist: sh ; extra == 'dev'
Requires-Dist: apache-airflow ; extra == 'dev'
Provides-Extra: kubernetes
Requires-Dist: apache-airflow <2.8,>=2.3 ; extra == 'kubernetes'
Requires-Dist: apache-airflow-providers-cncf-kubernetes ; extra == 'kubernetes'
